{
  "project_info": {
    "project_number": "864378831475",
    "project_id": "wlotim",
    "storage_bucket": "wlotim.appspot.com"
  },
  "client": [
    {
      "client_info": {
        "mobilesdk_app_id": "1:864378831475:android:a12bd56c59f866b4a16006",
        "android_client_info": {
          "package_name": "com.example.wlotim"
        }
      },
      "oauth_client": [
        {
          "client_id": "864378831475-rlh9hqkkst4gaooud330c14thld1gt96.apps.googleusercontent.com",
          "client_type": 3
        }
      ],
      "api_key": [
        {
          "current_key": "AIzaSyDkAvSGdX3RrfigXZHhroRrghU2XVQ9EwU"
        }
      ],
      "services": {
        "appinvite_service": {
          "other_platform_oauth_client": [
            {
              "client_id": "864378831475-rlh9hqkkst4gaooud330c14thld1gt96.apps.googleusercontent.com",
              "client_type": 3
            },
            {
              "client_id": "864378831475-17csjcjc0lv1gcv7ahpbvagudgkvtgdp.apps.googleusercontent.com",
              "client_type": 2,
              "ios_info": {
                "bundle_id": "com.example.wlotim"
              }
            }
          ]
        }
      }
    }
  ],
  "configuration_version": "1"
}